kalsievelib/__init__.py
kalsievelib/commands.py
kalsievelib/digest_md5.py
kalsievelib/factory.py
kalsievelib/managesieve.py
kalsievelib/parser.py
kalsievelib/tools.py
kalsievelib/tests/__init__.py
kalsievelib/tests/test_factory.py
kalsievelib/tests/test_managesieve.py
kalsievelib/tests/test_parser.py
kalsievelib/tests/files/utf8_sieve.txt
kalsievelib-1.4.1.dist-info/COPYING
kalsievelib-1.4.1.dist-info/METADATA
kalsievelib-1.4.1.dist-info/WHEEL
kalsievelib-1.4.1.dist-info/top_level.txt
kalsievelib-1.4.1.dist-info/RECORD
